pefetch/__init__.py
pefetch/cli.py
pefetch/html.py
pefetch/latex.py
pefetch-0.0.2.dist-info/METADATA
pefetch-0.0.2.dist-info/WHEEL
pefetch-0.0.2.dist-info/entry_points.txt
pefetch-0.0.2.dist-info/licenses/LICENSE.md
pefetch-0.0.2.dist-info/RECORD
