Metadata-Version: 2.4
Name: pefetch
Version: 0.0.2
Summary: Fetch Project Euler problems from the command line
Project-URL: Repository, https://github.com/stanfromireland/pefetch.git
Project-URL: Bug Tracker, https://github.com/stanfromireland/pefetch/issues
Project-URL: Changelog, https://github.com/stanfromireland/pefetch/blob/master/CHANGELOG.md
Author: Stan Ulbrych
Maintainer: Stan Ulbrych
License-Expression: MIT
License-File: LICENSE.md
Keywords: cli,projecteuler,utility
Classifier: Development Status :: 4 - Beta
Classifier: Programming Language :: Python
Requires-Python: >=3.8
